Metadata-Version: 2.1
Name: olutils
Version: 2.1.0
Summary: tools for common operations in a module
Home-page: https://github.com/OctaveLauby/olutils
Author: Octave Lauby
Author-email: 
License: Apache 2.0
Keywords: utils tools
Platform: UNKNOWN
Classifier: Intended Audience :: Developers
Classifier: Programming Language :: Python :: 3
Classifier: Programming Language :: Python :: 3.8
Classifier: Operating System :: OS Independent
Requires-Dist: numpy (>=1.10.0)
Requires-Dist: python-dateutil (>=2.8.0)
